LICENSE
MANIFEST.in
README.rst
setup.py
smart_open/__init__.py
smart_open/hdfs.py
smart_open/http.py
smart_open/s3.py
smart_open/smart_open_lib.py
smart_open/webhdfs.py
smart_open/tests/__init__.py
smart_open/tests/test_hdfs.py
smart_open/tests/test_s3.py
smart_open/tests/test_smart_open.py
smart_open/tests/test_data/crime-and-punishment.txt.gz
smart_open/tests/test_data/crlf_at_1k_boundary.warc.gz
srcd_smart_open.egg-info/PKG-INFO
srcd_smart_open.egg-info/SOURCES.txt
srcd_smart_open.egg-info/dependency_links.txt
srcd_smart_open.egg-info/requires.txt
srcd_smart_open.egg-info/top_level.txt