Metadata-Version: 2.1
Name: srcd_smart_open
Version: 1.9.0
Summary: Utils for streaming large files (S3, HDFS, gzip, bz2...) - temporary source{d} fork
Home-page: https://github.com/piskvorky/smart_open
Author: Radim Rehurek
Author-email: me@radimrehurek.com
Maintainer: Radim Rehurek
Maintainer-email: me@radimrehurek.com
License: MIT
Download-URL: http://pypi.python.org/pypi/smart_open
Keywords: file streaming,s3,hdfs
Platform: any
Classifier: Development Status :: 4 - Beta
Classifier: Environment :: Console
Classifier: Intended Audience :: Developers
Classifier: License :: OSI Approved :: MIT License
Classifier: Operating System :: OS Independent
Classifier: Programming Language :: Python :: 2.7
Classifier: Programming Language :: Python :: 3.5
Classifier: Programming Language :: Python :: 3.6
Classifier: Programming Language :: Python :: 3.7
Classifier: Topic :: System :: Distributed Computing
Classifier: Topic :: Database :: Front-Ends
Provides-Extra: test
